searchunify/__init__.py
searchunify/main.py
searchunify/client/__init__.py
searchunify/client/client.py
searchunify/core/__init__.py
searchunify/core/analytics/__init__.py
searchunify/core/analytics/analytics.py
searchunify/core/auth/__init__.py
searchunify/core/auth/auth_header_type.py
searchunify/core/auth/oauth2.py
searchunify/core/content/__init__.py
searchunify/core/content/contents.py
searchunify/core/search/__init__.py
searchunify/core/search/search.py
searchunify/utils/__init__.py
searchunify/utils/apis/__init__.py
searchunify/utils/apis/apis.py
searchunify/utils/constants/__init__.py
searchunify/utils/constants/constants.py
searchunify/utils/http_client/__init__.py
searchunify/utils/http_client/request_handler.py
searchunify/utils/validation/__init__.py
searchunify/utils/validation/analytics.py
searchunify/utils/validation/content.py
searchunify/utils/validation/oauth2.py
searchunify/utils/validation/search.py
searchunify-1.0.7.dist-info/LICENSE
searchunify-1.0.7.dist-info/METADATA
searchunify-1.0.7.dist-info/WHEEL
searchunify-1.0.7.dist-info/top_level.txt
searchunify-1.0.7.dist-info/RECORD
