Metadata-Version: 2.1
Name: searchunify
Version: 1.0.7
Summary: The SearchUnify SDK enables developers to easily work with the SearchUnify platform and build scalable solutions with search, analytics, crawlers and more.
Home-page: https://www.searchunify.com/
Author: SearchUnify
Author-email: ankur.mahajan@grazitti.com
License: MIT
Project-URL: Documentation, https://docs.searchunify.com/Content/Developer-Guides/SDKs-Python.htm
Project-URL: Source, https://github.com/searchunify/su-sdk-python
Platform: UNKNOWN
Classifier: Development Status :: 4 - Beta
Classifier: Intended Audience :: Developers
Classifier: Natural Language :: English
Classifier: License :: OSI Approved :: MIT License
Classifier: Programming Language :: Python
Classifier: Programming Language :: Python :: 3
Classifier: Programming Language :: Python :: 3.7
Classifier: Programming Language :: Python :: 3.8
Classifier: Programming Language :: Python :: 3.9
Classifier: Programming Language :: Python :: 3.10
Classifier: Programming Language :: Python :: 3.11
Requires-Python: >= 3
Requires-Dist: requests (==2.23.0)
Requires-Dist: schema (==0.7.4)
